fresco_static/__init__.py
fresco_static/cistr.py
fresco_static/test_fresco_static.py
fresco_static/views.py
fresco_static-0.5.dist-info/LICENSE.txt
fresco_static-0.5.dist-info/METADATA
fresco_static-0.5.dist-info/WHEEL
fresco_static-0.5.dist-info/top_level.txt
fresco_static-0.5.dist-info/RECORD
