Metadata-Version: 2.1
Name: fresco-static
Version: 0.5
Summary: Static file handling for fresco
Author: Oliver Cope
Author-email: oliver@redgecko.org
License: Apache
Classifier: Development Status :: 4 - Beta
Classifier: Environment :: Web Environment
Classifier: Intended Audience :: Developers
Classifier: License :: OSI Approved :: BSD License
Classifier: Operating System :: OS Independent
Classifier: Programming Language :: Python
Classifier: Topic :: Internet :: WWW/HTTP :: Dynamic Content
Classifier: Topic :: Internet :: WWW/HTTP :: WSGI
Classifier: Topic :: Software Development :: Libraries :: Python Modules
License-File: LICENSE.txt
Requires-Dist: fresco
Requires-Dist: portalocker
